prudentia_user_service/__init__.py
prudentia_user_service/api/__init__.py
prudentia_user_service/api/default/__init__.py
prudentia_user_service/api/default/create_user.py
prudentia_user_service/api/default/get_user.py
prudentia_user_service/client.py
prudentia_user_service/errors.py
prudentia_user_service/models/__init__.py
prudentia_user_service/models/http_validation_error.py
prudentia_user_service/models/user.py
prudentia_user_service/models/validation_error.py
prudentia_user_service/py.typed
prudentia_user_service/types.py
client_sdk-0.1.1.dist-info/METADATA
client_sdk-0.1.1.dist-info/WHEEL
client_sdk-0.1.1.dist-info/RECORD
